fretwork/__init__.py
fretwork/audio.py
fretwork/log.py
fretwork/task.py
fretwork/timer.py
fretwork/unicode.py
fretwork/version.py
fretwork/midi/DataTypeConverters.py
fretwork/midi/EventDispatcher.py
fretwork/midi/MidiFileParser.py
fretwork/midi/MidiInFile.py
fretwork/midi/MidiInStream.py
fretwork/midi/MidiOutFile.py
fretwork/midi/MidiOutStream.py
fretwork/midi/MidiToText.py
fretwork/midi/RawInstreamFile.py
fretwork/midi/RawOutstreamFile.py
fretwork/midi/__init__.py
fretwork/midi/constants.py
fretwork/mixstream/SDL.dll
fretwork/mixstream/SDL_mixer.dll
fretwork/mixstream/_MixStream.cp37-win32.pyd
fretwork/mixstream/__init__.py
fretwork/mixstream/iconv.dll
fretwork/mixstream/libSoundTouch-0.dll
fretwork/mixstream/libglib-2.0-0.dll
fretwork/mixstream/libgthread-2.0-0.dll
fretwork/mixstream/libintl-8.dll
fretwork/mixstream/libogg-0.dll
fretwork/mixstream/libtheora-0.dll
fretwork/mixstream/libvorbis-0.dll
fretwork/mixstream/libvorbisfile-3.dll
fretwork/mixstream/zlib1.dll
fretwork-0.5.0.dist-info/LICENSE
fretwork-0.5.0.dist-info/METADATA
fretwork-0.5.0.dist-info/WHEEL
fretwork-0.5.0.dist-info/top_level.txt
fretwork-0.5.0.dist-info/RECORD
