Metadata-Version: 2.0
Name: fretwork
Version: 0.5.0
Summary: Game library used by FoFiX, and FoF:R.
Home-page: https://github.com/fofix/fretwork
Author: FoFiX team
Author-email: contact@fofix.org
License: GPLv2+
Keywords: music engine fofix frets game
Platform: UNKNOWN
Classifier: Intended Audience :: Developers
Classifier: License :: OSI Approved :: GNU General Public License v2 or later (GPLv2+)
Classifier: Programming Language :: Python
Classifier: Programming Language :: Python :: 2
Classifier: Programming Language :: Python :: 2.7
Classifier: Programming Language :: Python :: 3
Classifier: Programming Language :: Python :: 3.6
Classifier: Programming Language :: Python :: 3.7
Classifier: Programming Language :: Python :: 3.8
Classifier: Topic :: Multimedia
Classifier: Topic :: Multimedia :: Sound/Audio
Classifier: Topic :: Software Development :: Libraries
Requires-Dist: Cython (<3.0,>=0.29.2)
Requires-Dist: Pygame (<2.0)
Requires-Dist: PyOpenGL
Requires-Dist: numpy (<1.17); python_version < "3.4"
Requires-Dist: numpy (<1.20); python_version == "3.6"
Requires-Dist: numpy; python_version > "3.6"
